<title>MathEval & MathEval.Fast 代码审查报告</title>

<callout emoji="📝" background-color="light-blue" border-color="blue">
<p>对两个项目的所有源文件进行了逐行审查，并通过交叉验证确认了 14 个问题。按严重程度分级：严重 5 个、中等 4 个、轻微 5 个。</p>
</callout>

<hr/>

<h1>严重 BUG（5 个）</h1>

<h2>BUG-1：FastEvaluator 链式短路求值导致解析崩溃</h2>

<p><b>位置</b>：FastEvaluator.cs（EvalLogicalOr、EvalLogicalAnd）</p>

<p><b>问题</b>：短路触发时直接 <code>return 1.0</code>/<code>return 0.0</code>，未消费链中剩余的操作符。</p>

<pre lang="csharp" caption="EvalLogicalOr 短路逻辑"><code>// EvalLogicalOr
if (!_skipMode &amp;&amp; ConvertToBool(left)) {
    _skipMode = true;
    EvalLogicalAnd();      // 仅跳过当前右操作数
    _skipMode = false;
    return 1.0;            // 直接返回！链中剩余的 || 未被消费
}</code></pre>

<p><b>复现</b>：<code>1 || 2 || 3</code></p>
<ul>
<li><code>left = 1</code>（true）→ 短路，跳过 <code>2</code>，<code>return 1.0</code></li>
<li>回到 <code>Evaluate()</code> 时 <code>|| 3</code> 仍未消费 → 抛出 <code>意外的字符 '|'</code></li>
</ul>

<p><b>影响</b>：任何含 3 个及以上操作数的 <code>||</code>/<code>&amp;&amp;</code>/<code>or</code>/<code>and</code> 链在短路时都会崩溃。</p>

<h2>BUG-2：FastEvaluator skipMode 下位运算/算术运算未跳过</h2>

<p><b>位置</b>：FastEvaluator.cs（位运算方法、EvalAdditive）</p>

<p><b>问题</b>：<code>_skipMode</code> 仅在 <code>EvalMultiplicative</code>、<code>EvalPower</code>、<code>LookupVariable</code> 中检查。位运算方法（<code>EvalBitwiseOr/Xor/And/Shift</code>）、<code>EvalAdditive</code>、<code>EvalEquality</code>、<code>EvalRelational</code> 均未检查，会执行实际运算。</p>

<pre lang="csharp" caption="EvalBitwiseOr - 无 _skipMode 检查"><code>// EvalBitwiseOr - 无 _skipMode 检查
left = BuiltInOperators.BitwiseOr(left, right);  // skipMode 下仍调用</code></pre>

<p><b>复现</b>：<code>1 ? 2 : 3.5 | x</code>（x 未定义）</p>
<ul>
<li>true 分支求值 <code>2</code> 后，skipMode 跳过 false 分支</li>
<li>false 分支 <code>3.5 | x</code>：<code>LookupVariable(x)</code> 返回 0，但 <code>BuiltInOperators.BitwiseOr(3.5, 0)</code> 调用 <code>ToInt64(3.5)</code> → <b>抛异常</b>（3.5 非整数）</li>
</ul>

<p><b>影响</b>：短路跳过的分支若含位运算/算术运算且操作数不合法，会错误抛异常。</p>

<h2>BUG-3：TypeHelper.ToInteger 仅支持 double 类型</h2>

<p><b>位置</b>：TypeHelper.cs（ToInteger 方法）</p>

<p><b>问题</b>：<code>ToDouble</code> 支持 12 种数值类型，但 <code>ToInteger</code> 仅处理 <code>double</code>，其余类型直接抛异常。</p>

<pre lang="csharp" caption="ToInteger 仅处理 double"><code>public static long ToInteger(object value, string operationName) {
    if (value is double d) {           // 仅处理 double
        if (d == Math.Truncate(d) &amp;&amp; !double.IsInfinity(d) &amp;&amp; !double.IsNaN(d))
            return (long)d;
    }
    throw new TypeMismatchException(...);  // int/long/float 等全部抛异常
}</code></pre>

<p><b>复现</b>：通过 <code>SetVariable("x", 5)</code>（int 类型）设置变量后执行 <code>x &amp; 3</code></p>
<ul>
<li><code>EvaluateBinary</code> 调用 <code>ToInteger(left=5(int), "按位与")</code> → <b>抛 TypeMismatchException</b></li>
</ul>

<p><b>影响</b>：任何通过 API 设置的非 double 整数变量参与位运算/移位都会失败。</p>

<h2>BUG-4：IndexPushdownOptimizer 无条件下推索引到函数参数，破坏聚合函数语义</h2>

<p><b>位置</b>：IndexPushdownOptimizer.cs</p>

<p><b>问题</b>：将 <code>f(a)[i]</code> 无条件转换为 <code>f(a[i])</code>，对聚合函数（sum/max/min）语义错误。</p>

<pre lang="csharp" caption="索引下推对所有函数一视同仁"><code>// f(a)[i] → f(a[i])  对所有函数一视同仁
ArrayIndexExpression { Array: FunctionCall func, Index: var idx }
    => Optimize(new FunctionCall(func.Name,
        func.Arguments.Select(arg => arg is ValueExpression
            ? arg
            : new ArrayIndexExpression(arg, idx)).ToList())),</code></pre>

<p><b>复现</b>：<code>max([a, b])[0]</code>（a、b 为数组变量）</p>
<ul>
<li>原始语义：<code>max([a, b])</code> 返回 element-wise 最大值数组，<code>[0]</code> 取首元素</li>
<li>优化后：<code>max([a[0], b[0]])</code> 返回标量最大值</li>
<li>两者结果不同</li>
</ul>

<p><b>影响</b>：聚合函数与索引组合时结果错误。且此优化在 <code>Calculator.EnsureParsed</code> 中<b>无条件调用</b>，不受 <code>ExpressionOptions</code> 控制。</p>

<h2>BUG-5：CompiledExpression 编译模式缺少数组广播</h2>

<p><b>位置</b>：CompiledExpression.cs（CompileFunctionCall 方法）</p>

<p><b>问题</b>：<code>CompileFunctionCall</code> 直接调用 <code>ExpressionFunction(object[])</code>，未实现 EvaluationVisitor 中的数组广播逻辑。</p>

<pre lang="csharp" caption="CompiledExpression - 无数组广播"><code>// CompiledExpression - 无数组广播
var invokeExpr = LinqExpression.Invoke(funcVar, argsArrayVar);</code></pre>

<p>对比解释模式：</p>
<pre lang="csharp" caption="EvaluationVisitor - 有数组广播"><code>// EvaluationVisitor - 有数组广播
var arrayArg = args.FirstOrDefault(a => a is double[]);
if (arrayArg is double[] arr) {
    // element-wise 广播
}</code></pre>

<p><b>影响</b>：<code>CompileOptimization</code> 标志启用后，<code>sin([1,2,3])</code> 等数组函数调用行为与解释模式不一致，可能抛异常或返回错误结果。</p>

<hr/>

<h1>中等 BUG（4 个）</h1>

<h2>BUG-6：BytecodeVM 除零不抛异常，与主项目行为不一致</h2>

<p><b>位置</b>：BytecodeVM.cs、BuiltInOperators.cs（IntegerDivide 方法）</p>

<p><b>问题</b>：<code>OpCode.Div</code> 直接执行 <code>stack[sp-1] /= r</code>，除零返回 Infinity/NaN 而非异常。</p>

<table>
<colgroup><col span="2" width="200"/></colgroup>
<thead><tr><th background-color="light-gray">表达式</th><th background-color="light-gray">MathEval 主项目</th><th background-color="light-gray">MathEval.Fast VM</th></tr></thead>
<tbody>
<tr><td><code>1/0</code></td><td><code>DivisionByZeroException</code></td><td><code>Infinity</code></td></tr>
<tr><td><code>1//0</code></td><td><code>DivisionByZeroException</code></td><td><code>Infinity</code>（IntegerDivide 未检查）</td></tr>
</tbody>
</table>

<p>主项目 TypeHelper.cs 明确检查 <code>if (d2 == 0) throw new DivisionByZeroException()</code>。</p>

<h2>BUG-7：BuiltInOperators.Power 未校验操作数</h2>

<p><b>位置</b>：BuiltInOperators.cs（Power 方法）</p>

<p><b>问题</b>：直接调用 <code>Math.Pow</code>，未校验负底数非整数次幂、零的负次幂。</p>

<table>
<colgroup><col span="2" width="200"/></colgroup>
<thead><tr><th background-color="light-gray">表达式</th><th background-color="light-gray">MathEval 主项目</th><th background-color="light-gray">MathEval.Fast</th></tr></thead>
<tbody>
<tr><td><code>(-2) ^ 0.5</code></td><td><code>EvaluateException</code>（不能对负数求非整数次幂）</td><td><code>NaN</code></td></tr>
<tr><td><code>0 ^ -1</code></td><td><code>EvaluateException</code>（零不能求负数次幂）</td><td><code>Infinity</code></td></tr>
</tbody>
</table>

<p>主项目 TypeHelper.cs 有完整校验。</p>

<h2>BUG-8：CompiledExpression.CompileArrayIndex 未检查越界</h2>

<p><b>位置</b>：CompiledExpression.cs（CompileArrayIndex 方法）</p>

<p><b>问题</b>：编译为原生数组访问，越界抛 <code>IndexOutOfRangeException</code>，而非友好的 <code>EvaluateException</code>。</p>

<pre lang="csharp" caption="编译模式 - 越界抛原生异常"><code>var arrayAccess = LinqExpression.ArrayIndex(
    LinqExpression.Convert(arrayVar, typeof(double[])),
    intIndex);  // 越界 → IndexOutOfRangeException</code></pre>

<p>对比解释模式 EvaluationVisitor.cs：</p>
<pre lang="csharp" caption="解释模式 - 友好的越界错误"><code>if (intIndex &lt; 0 || intIndex &gt;= arr.Length)
    throw new EvaluateException($"索引 {intIndex} 超出数组范围 [0, {arr.Length})");</code></pre>

<h2>BUG-9：EvaluationVisitor 多数组广播未校验长度一致</h2>

<p><b>位置</b>：EvaluationVisitor.cs（Visit FunctionCall）</p>

<p><b>问题</b>：数组广播仅取第一个数组参数的长度，其他数组参数直接用 <code>da[i]</code> 访问，未校验长度。</p>

<pre lang="csharp" caption="多数组广播未校验长度"><code>var arrayArg = args.FirstOrDefault(a => a is double[]);  // 只取第一个数组
if (arrayArg is double[] arr) {
    var result = new double[arr.Length];
    for (int i = 0; i &lt; arr.Length; i++) {
        for (int j = 0; j &lt; args.Length; j++) {
            scalarArgs[j] = args[j] is double[] da ? da[i] : args[j];  // da[i] 可能越界
        }
    }
}</code></pre>

<p><b>复现</b>：<code>max([1,2,3], [1,2])</code> → i=2 时 <code>da[2]</code> 越界，抛 <code>IndexOutOfRangeException</code> 而非长度不匹配的友好错误。</p>

<hr/>

<h1>轻微问题（5 个）</h1>

<h2>BUG-10：BytecodeVM 返回值使用 stack[0] 而非 stack[sp-1]</h2>

<p><b>位置</b>：BytecodeVM.cs（Execute 方法末尾）</p>

<pre lang="csharp" caption="返回值取栈底而非栈顶"><code>return sp &gt; 0 ? stack[0] : 0.0;  // 应为 stack[sp - 1]</code></pre>

<p>正常编译的字节码最终 <code>sp=1</code>，两者等价。但若因编译器缺陷导致栈不平衡，<code>stack[0]</code> 会返回错误值。<code>stack[sp-1]</code> 是更安全、语义更正确的写法。</p>

<h2>BUG-11：FastScanner.ReadDecimal 未校验无效数字格式</h2>

<p><b>位置</b>：FastScanner.cs（ReadDecimal 方法）</p>

<p><b>问题</b>：<code>1e</code>、<code>1e+</code>、<code>.</code> 等无效格式会被扫描器接受，随后 <code>double.Parse</code> 抛 <code>FormatException</code> 而非 <code>FastEvalException</code>，违反异常一致性。</p>

<h2>BUG-12：OptimizedExpressionCache.GetOrAddCompiled 存在竞态条件</h2>

<p><b>位置</b>：OptimizedExpressionCache.cs（GetOrAddCompiled 方法）</p>

<pre lang="csharp" caption="竞态条件 - 可能重复编译"><code>if (entry.Compiled != null) return entry.Compiled;
var compiledExpr = compileFactory(entry.Ast!);
entry.Compiled = compiledExpr;  // 多线程下可能重复编译</code></pre>

<p>多线程同时进入时可能重复执行 <code>compileFactory</code>，浪费资源（结果仍正确）。</p>

<h2>BUG-13：ExpressionCache 无容量限制，存在内存泄漏风险</h2>

<p><b>位置</b>：ExpressionCache.cs、OptimizedExpressionCache.cs</p>

<pre lang="csharp" caption="静态缓存无容量上限"><code>private static readonly ConcurrentDictionary&lt;string, LogicalExpression&gt; _cache = new();</code></pre>

<p>静态缓存无容量上限，求值大量不同表达式时缓存无限增长。建议引入 LRU 策略（参考 MathEval.Fast 的 <code>LruCache</code>）。</p>

<h2>BUG-14：TypeMismatchException 继承层次可能引起混淆</h2>

<p><b>位置</b>：TypeMismatchException.cs</p>

<p><code>TypeMismatchException</code> 在求值过程中抛出（如 <code>ToInteger</code> 失败），但直接继承 <code>MathEvalException</code> 而非 <code>EvaluateException</code>。用户用 <code>catch (EvaluateException)</code> 捕获求值错误时会漏掉此异常。</p>

<callout emoji="📌" background-color="light-yellow" border-color="yellow">
<p>注：<code>ExceptionTests.cs</code> 明确验证了此继承关系，应为有意设计。列为观察项供参考。</p>
</callout>

<hr/>

<h1>汇总</h1>

<table>
<colgroup><col span="1" width="60"/><col span="1" width="80"/><col span="1" width="80"/><col span="1" width="200"/><col span="1" width="280"/></colgroup>
<thead><tr>
<th background-color="light-gray">编号</th>
<th background-color="light-gray">严重程度</th>
<th background-color="light-gray">项目</th>
<th background-color="light-gray">位置</th>
<th background-color="light-gray">简述</th>
</tr></thead>
<tbody>
<tr><td>BUG-1</td><td><span text-color="red">严重</span></td><td>Fast</td><td>FastEvaluator.cs</td><td>链式短路未消费剩余操作符，导致崩溃</td></tr>
<tr><td>BUG-2</td><td><span text-color="red">严重</span></td><td>Fast</td><td>FastEvaluator.cs</td><td>skipMode 下位运算/算术未跳过</td></tr>
<tr><td>BUG-3</td><td><span text-color="red">严重</span></td><td>MathEval</td><td>TypeHelper.cs</td><td>ToInteger 仅支持 double 类型</td></tr>
<tr><td>BUG-4</td><td><span text-color="red">严重</span></td><td>MathEval</td><td>IndexPushdownOptimizer.cs</td><td>索引下推破坏聚合函数语义</td></tr>
<tr><td>BUG-5</td><td><span text-color="red">严重</span></td><td>MathEval</td><td>CompiledExpression.cs</td><td>编译模式缺数组广播</td></tr>
<tr><td>BUG-6</td><td><span text-color="orange">中等</span></td><td>Fast</td><td>BytecodeVM.cs / BuiltInOperators.cs</td><td>除零不抛异常</td></tr>
<tr><td>BUG-7</td><td><span text-color="orange">中等</span></td><td>Fast</td><td>BuiltInOperators.cs</td><td>幂运算未校验操作数</td></tr>
<tr><td>BUG-8</td><td><span text-color="orange">中等</span></td><td>MathEval</td><td>CompiledExpression.cs</td><td>数组索引未检查越界</td></tr>
<tr><td>BUG-9</td><td><span text-color="orange">中等</span></td><td>MathEval</td><td>EvaluationVisitor.cs</td><td>多数组广播未校验长度</td></tr>
<tr><td>BUG-10</td><td><span text-color="gray">轻微</span></td><td>Fast</td><td>BytecodeVM.cs</td><td>返回值 stack[0] 应为 stack[sp-1]</td></tr>
<tr><td>BUG-11</td><td><span text-color="gray">轻微</span></td><td>Fast</td><td>FastScanner.cs</td><td>数字格式校验缺失</td></tr>
<tr><td>BUG-12</td><td><span text-color="gray">轻微</span></td><td>MathEval</td><td>OptimizedExpressionCache.cs</td><td>缓存竞态条件</td></tr>
<tr><td>BUG-13</td><td><span text-color="gray">轻微</span></td><td>MathEval</td><td>ExpressionCache.cs</td><td>缓存无容量限制</td></tr>
<tr><td>BUG-14</td><td><span text-color="gray">轻微</span></td><td>MathEval</td><td>TypeMismatchException.cs</td><td>异常继承层次（有意设计）</td></tr>
</tbody>
</table>

<hr/>

<callout emoji="✅" background-color="light-green" border-color="green">
<p>审查报告已完成。如需修复其中任何 BUG，可从最严重的 BUG-1 开始逐一修复。</p>
</callout>
